{
  "hash": "eeaed607",
  "configHash": "0c480d03",
  "lockfileHash": "43a67d3b",
  "browserHash": "239c66ce",
  "optimized": {
    "wangeditor": {
      "src": "../../../../../node_modules/wangeditor/dist/wangEditor.js",
      "file": "wangeditor.js",
      "fileHash": "04eafd50",
      "needsInterop": true
    },
    "marked": {
      "src": "../../../../../node_modules/marked/lib/marked.esm.js",
      "file": "marked.js",
      "fileHash": "66048a9a",
      "needsInterop": false
    },
    "antd/es/list/Item": {
      "src": "../../../../../../../../../../node_modules/antd/es/list/Item.js",
      "file": "antd_es_list_Item.js",
      "fileHash": "d2d1c216",
      "needsInterop": false
    },
    "turndown": {
      "src": "../../../../../node_modules/turndown/lib/turndown.browser.es.js",
      "file": "turndown.js",
      "fileHash": "be43164d",
      "needsInterop": false
    },
    "html-to-md": {
      "src": "../../../../../node_modules/html-to-md/dist/index.js",
      "file": "html-to-md.js",
      "fileHash": "050ff875",
      "needsInterop": true
    }
  },
  "chunks": {
    "chunk-LNEMQRCO": {
      "file": "chunk-LNEMQRCO.js"
    }
  }
}